hksc_disassembler/__init__.py
hksc_disassembler/cli/__init__.py
hksc_disassembler/cli/disassembler.py
hksc_disassembler/cli/instruction_printer.py
hksc_disassembler/common/__init__.py
hksc_disassembler/common/reader.py
hksc_disassembler/loader/__init__.py
hksc_disassembler/loader/hs.py
hksc_disassembler/loader/hs_constant.py
hksc_disassembler/loader/hs_debug.py
hksc_disassembler/loader/hs_enum.py
hksc_disassembler/loader/hs_function.py
hksc_disassembler/loader/hs_header.py
hksc_disassembler/loader/hs_instruction.py
hksc_disassembler/loader/hs_opcodes.py
hksc_disassembler/loader/hs_structure.py
hksc_disassembler/loader/hs_type_reader.py
hksc_disassembler-0.2.3.dist-info/LICENSE.txt
hksc_disassembler-0.2.3.dist-info/METADATA
hksc_disassembler-0.2.3.dist-info/WHEEL
hksc_disassembler-0.2.3.dist-info/entry_points.txt
hksc_disassembler-0.2.3.dist-info/top_level.txt
hksc_disassembler-0.2.3.dist-info/RECORD
