Metadata-Version: 2.1
Name: hksc_disassembler
Version: 0.2.3
Summary: A HavokScript 5.1 Disassembler
Author: Surasia
License: GNU GENERAL PUBLIC LICENSE
Project-URL: Repository, https://github.com/Surasia/hksc-disassembler
Project-URL: Issues, https://github.com/Surasia/hksc-disassembler/issues
Project-URL: Changelog, https://github.com/Surasia/hksc-disassembler/blob/master/CHANGELOG.md
Keywords: HavokScript,hksc,lua,lua script,scripting,disassembler
Classifier: Typing :: Typed
Classifier: Programming Language :: Python :: 3.10
Classifier: Programming Language :: Python :: 3.11
Classifier: Programming Language :: Python :: 3.12
Classifier: License :: OSI Approved :: GNU General Public License v3 (GPLv3)
Classifier: Operating System :: Microsoft :: Windows
Classifier: Intended Audience :: Developers
Classifier: Development Status :: 3 - Alpha
Requires-Python: >=3.10.0
License-File: LICENSE.txt
Requires-Dist: click ~=8.1.7
